README.md
README.rst
setup.py
adapters/__init__.py
adapters/base.py
adapters/credentials.py
adapters/enums.py
adapters/factory.py
adapters/telegram/__init__.py
adapters/telegram/adapter.py
adapters/telegram/credentials.py
adapters/vk/__init__.py
adapters/vk/adapter.py
adapters/vk/credentials.py
async_bot_api_adapters.egg-info/PKG-INFO
async_bot_api_adapters.egg-info/SOURCES.txt
async_bot_api_adapters.egg-info/dependency_links.txt
async_bot_api_adapters.egg-info/requires.txt
async_bot_api_adapters.egg-info/top_level.txt