Metadata-Version: 1.0
Name: async-bot-api-adapters
Version: 0.0.1
Summary: Common interface for vk/telegram api calls
Home-page: UNKNOWN
Author: Sergey Konik
Author-email: s.konik.job@gmail.com
License: UNKNOWN
Platform: UNKNOWN
